pysnitch/__init__.py
pysnitch/cli.py
pysnitch/pysnitch.py
pysnitch-0.1.0.dist-info/AUTHORS.rst
pysnitch-0.1.0.dist-info/LICENSE
pysnitch-0.1.0.dist-info/METADATA
pysnitch-0.1.0.dist-info/WHEEL
pysnitch-0.1.0.dist-info/entry_points.txt
pysnitch-0.1.0.dist-info/top_level.txt
pysnitch-0.1.0.dist-info/RECORD
