Metadata-Version: 2.1
Name: pysnitch
Version: 0.1.0
Summary: Python dependency CVE scanner
Home-page: https://github.com/doc-E-brown/pysnitch
Author: Ben Johnston
Author-email: bjohnston@neomailbox.net
License: GNU General Public License v3
Keywords: pysnitch
Platform: UNKNOWN
Classifier: Development Status :: 2 - Pre-Alpha
Classifier: Intended Audience :: Developers
Classifier: License :: OSI Approved :: GNU General Public License v3 (GPLv3)
Classifier: Natural Language :: English
Classifier: Programming Language :: Python :: 3
Classifier: Programming Language :: Python :: 3.5
Classifier: Programming Language :: Python :: 3.6
Classifier: Programming Language :: Python :: 3.7
Classifier: Programming Language :: Python :: 3.8
Requires-Python: >=3.5
Requires-Dist: Click (>=7.0)
